powerline_exitstatus/__init__.py
powerline_exitstatus/segments.py
powerline_exitstatus-1.1.0.dist-info/METADATA
powerline_exitstatus-1.1.0.dist-info/RECORD
powerline_exitstatus-1.1.0.dist-info/WHEEL
powerline_exitstatus-1.1.0.dist-info/top_level.txt
